catalogue/__init__.py
catalogue/registry.py
catalogue/_importlib_metadata/__init__.py
catalogue/_importlib_metadata/_compat.py
catalogue/config/__init__.py
catalogue/config/config.py
catalogue/config/util.py
catalogue/tests/__init__.py
catalogue/tests/conftest.py
catalogue/tests/test_catalogue.py
catalogue/tests/test_config.py
catalogue/tests/util.py
catalogue-2.1.0.dist-info/LICENSE
catalogue-2.1.0.dist-info/METADATA
catalogue-2.1.0.dist-info/WHEEL
catalogue-2.1.0.dist-info/top_level.txt
catalogue-2.1.0.dist-info/zip-safe
catalogue-2.1.0.dist-info/RECORD
