Metadata-Version: 2.1
Name: catalogue
Version: 2.1.0
Summary: Lightweight function registries for your library
Home-page: https://github.com/explosion/catalogue
Author: Explosion
Author-email: contact@explosion.ai
License: MIT
Classifier: Development Status :: 5 - Production/Stable
Classifier: Environment :: Console
Classifier: Intended Audience :: Developers
Classifier: Intended Audience :: Science/Research
Classifier: License :: OSI Approved :: MIT License
Classifier: Operating System :: POSIX :: Linux
Classifier: Operating System :: MacOS :: MacOS X
Classifier: Operating System :: Microsoft :: Windows
Classifier: Programming Language :: Python :: 3
Classifier: Programming Language :: Python :: 3.6
Classifier: Programming Language :: Python :: 3.7
Classifier: Programming Language :: Python :: 3.8
Classifier: Programming Language :: Python :: 3.9
Classifier: Programming Language :: Python :: 3.10
Classifier: Topic :: Scientific/Engineering
Requires-Python: >=3.6
License-File: LICENSE
Requires-Dist: zipp (>=0.5) ; python_version < "3.8"
Requires-Dist: typing-extensions (>=3.6.4) ; python_version < "3.8"
